abstract_solcatcher_database/__init__.py
abstract_solcatcher_database/db_funcs.py
abstract_solcatcher_database/pair_updates.py
abstract_solcatcher_database/connect/__init__.py
abstract_solcatcher_database/connect/columns.py
abstract_solcatcher_database/connect/core.py
abstract_solcatcher_database/connect/fetch.py
abstract_solcatcher_database/connect/introspection.py
abstract_solcatcher_database/connect/pairs.py
abstract_solcatcher_database/connect/testConns.py
abstract_solcatcher_database/connect/connect/__init__.py
abstract_solcatcher_database/connect/connect/testConns.py
abstract_solcatcher_database/connect/connect/envs/__init__.py
abstract_solcatcher_database/connect/connect/envs/connections.py
abstract_solcatcher_database/connect/connect/envs/imports/__init__.py
abstract_solcatcher_database/connect/connect/envs/imports/constants.py
abstract_solcatcher_database/connect/connect/envs/imports/init_imports.py
abstract_solcatcher_database/connect/connect/envs/imports/utils.py
abstract_solcatcher_database/connect/connect/envs/queues/__init__.py
abstract_solcatcher_database/connect/connect/envs/queues/env.py
abstract_solcatcher_database/connect/connect/envs/settings/__init__.py
abstract_solcatcher_database/connect/connect/envs/settings/env.py
abstract_solcatcher_database/connect/connect/envs/solana/__init__.py
abstract_solcatcher_database/connect/connect/envs/solana/env.py
abstract_solcatcher_database/connect/envs/__init__.py
abstract_solcatcher_database/connect/envs/connections.py
abstract_solcatcher_database/connect/envs/imports/__init__.py
abstract_solcatcher_database/connect/envs/imports/constants.py
abstract_solcatcher_database/connect/envs/imports/init_imports.py
abstract_solcatcher_database/connect/envs/imports/utils.py
abstract_solcatcher_database/connect/envs/queues/__init__.py
abstract_solcatcher_database/connect/envs/queues/env.py
abstract_solcatcher_database/connect/envs/settings/__init__.py
abstract_solcatcher_database/connect/envs/settings/env.py
abstract_solcatcher_database-0.0.0.67.dist-info/METADATA
abstract_solcatcher_database-0.0.0.67.dist-info/WHEEL
abstract_solcatcher_database-0.0.0.67.dist-info/top_level.txt
abstract_solcatcher_database-0.0.0.67.dist-info/RECORD
